invisibleroads_scripts/__init__.py
invisibleroads_scripts/macros.py
invisibleroads_scripts/models.py
invisibleroads_scripts/routines.py
invisibleroads_scripts/settings.py
invisibleroads_scripts-2.0.6.dist-info/DESCRIPTION.rst
invisibleroads_scripts-2.0.6.dist-info/METADATA
invisibleroads_scripts-2.0.6.dist-info/RECORD
invisibleroads_scripts-2.0.6.dist-info/WHEEL
invisibleroads_scripts-2.0.6.dist-info/entry_points.txt
invisibleroads_scripts-2.0.6.dist-info/metadata.json
invisibleroads_scripts-2.0.6.dist-info/top_level.txt
invisibleroads_scripts-2.0.6.dist-info/zip-safe
