Metadata-Version: 2.0
Name: invisibleroads-scripts
Version: 2.0.6
Summary: Command-line scripts for managing your goals
Home-page: https://github.com/invisibleroads/invisibleroads-scripts
Author: Roy Hyunjin Han
Author-email: rhh@crosscompute.com
License: UNKNOWN
Keywords: invisibleroads
Platform: UNKNOWN
Classifier: Programming Language :: Python :: 3
Classifier: License :: OSI Approved :: MIT License
Classifier: Operating System :: OS Independent
Requires-Dist: invisibleroads
Requires-Dist: invisibleroads-macros
Requires-Dist: networkx
Requires-Dist: psycopg2
Requires-Dist: psycopg2-binary
Requires-Dist: pytz
Requires-Dist: sqlalchemy
